rag_agent_sdk/__init__.py
rag_agent_sdk/auth.py
rag_agent_sdk/client.py
rag_agent_sdk/config.py
rag_agent_sdk/datasets.py
rag_agent_sdk/documents.py
rag_agent_sdk/exceptions.py
rag_agent_sdk/graph.py
rag_agent_sdk/logging.py
rag_agent_sdk/mock.py
rag_agent_sdk/models.py
rag_agent_sdk/query.py
rag_agent_sdk/sync_client.py
rag_agent_sdk/utils/__init__.py
rag_agent_sdk/utils/http.py
rag_agent_sdk-0.1.1.dist-info/METADATA
rag_agent_sdk-0.1.1.dist-info/WHEEL
rag_agent_sdk-0.1.1.dist-info/RECORD
